{
  "gitSyncId": "67fe02ce08c30476df4545b1_543b90c5-bc2d-4997-9c08-7385e23dfe3b",
  "id": "Renewal Management_RiskRenewalJoin.deriveOutcomeCategory",
  "pluginId": "js-plugin",
  "pluginType": "JS",
  "unpublishedAction": {
    "actionConfiguration": {
      "encodeParamsToggle": true,
      "jsArguments": [
        {
          "name": "renewalOutcome"
        }
      ],
      "paginationType": "NONE",
      "timeoutInMillisecond": 10000
    },
    "collectionId": "Renewal Management_RiskRenewalJoin",
    "confirmBeforeExecute": false,
    "datasource": {
      "isAutoGenerated": false,
      "name": "UNUSED_DATASOURCE",
      "pluginId": "js-plugin"
    },
    "dynamicBindingPathList": [
      {
        "key": "body"
      }
    ],
    "fullyQualifiedName": "RiskRenewalJoin.deriveOutcomeCategory",
    "name": "deriveOutcomeCategory",
    "pageId": "Renewal Management",
    "runBehaviour": "MANUAL",
    "userSetOnLoad": false
  }
}