{
  "gitSyncId": "67fe02ce08c30476df4545b1_af5cb469-433d-478c-a499-d0e83955e3eb",
  "id": "Job Performance_UpdateJobDescrStatus",
  "pluginId": "postgres-plugin",
  "pluginType": "DB",
  "unpublishedAction": {
    "actionConfiguration": {
      "body": "SET TIME ZONE 'Europe/Berlin';\n\nUPDATE public.\"PerformanceAgentOutput\"\nSET \n  recommendation_status_job_description = {{this.params.status}}\nWHERE id = '{{CurrentAgentOutputID.text}}';\n",
      "encodeParamsToggle": true,
      "paginationType": "NONE",
      "pluginSpecifiedTemplates": [
        {
          "value": true
        }
      ],
      "timeoutInMillisecond": 10000
    },
    "confirmBeforeExecute": false,
    "datasource": {
      "id": "NeonTech",
      "isAutoGenerated": false,
      "name": "NeonTech",
      "pluginId": "postgres-plugin"
    },
    "dynamicBindingPathList": [
      {
        "key": "body"
      }
    ],
    "name": "UpdateJobDescrStatus",
    "pageId": "Job Performance",
    "runBehaviour": "MANUAL",
    "userSetOnLoad": false
  }
}