{
  "animateLoading": true,
  "borderRadius": "{{appsmith.theme.borderRadius.appBorderRadius}}",
  "bottomRow": 8,
  "dynamicBindingPathList": [
    {
      "key": "truncateButtonColor"
    },
    {
      "key": "fontFamily"
    },
    {
      "key": "borderRadius"
    }
  ],
  "dynamicHeight": "AUTO_HEIGHT",
  "dynamicTriggerPathList": [],
  "fontFamily": "{{appsmith.theme.fontFamily.appFont}}",
  "fontSize": "0.875rem",
  "fontStyle": "",
  "isLoading": false,
  "isVisible": true,
  "key": "22c8yb35ze",
  "leftColumn": 0,
  "maxDynamicHeight": 9000,
  "minDynamicHeight": 4,
  "minWidth": 450,
  "mobileBottomRow": 21,
  "mobileLeftColumn": 1,
  "mobileRightColumn": 17,
  "mobileTopRow": 17,
  "needsErrorInfo": false,
  "originalBottomRow": 77,
  "originalTopRow": 73,
  "overflow": "NONE",
  "parentColumnSpace": 9.8974609375,
  "parentId": "x9yzshdj2h",
  "parentRowSpace": 10,
  "renderMode": "CANVAS",
  "responsiveBehavior": "fill",
  "rightColumn": 22,
  "shouldTruncate": false,
  "text": "ATS Integration",
  "textAlign": "LEFT",
  "textColor": "#231F20",
  "topRow": 4,
  "truncateButtonColor": "{{appsmith.theme.colors.primaryColor}}",
  "type": "TEXT_WIDGET",
  "version": 1,
  "widgetId": "aptqc7ox8k",
  "widgetName": "Text25CopyCopy2"
}